pdm_shear-0.1.0.dist-info/METADATA
pdm_shear-0.1.0.dist-info/WHEEL
pdm_shear-0.1.0.dist-info/entry_points.txt
pdm_shear-0.1.0.dist-info/licenses/LICENSE
pdm_shear/__init__.py
pdm_shear/actions.py
pdm_shear/main.py
pdm_shear/parser.py
pdm_shear/plugin.py
pdm_shear-0.1.0.dist-info/RECORD
