Metadata-Version: 2.1
Name: pdm-shear
Version: 0.1.0
Summary: Detect and remove unused dependencies for Python projects
Keywords: pdm,pdm-plugin
Author-Email: Frost Ming <me@frostming.com>
License: MIT
Classifier: Programming Language :: Python :: 3
Classifier: Programming Language :: Python :: 3 :: Only
Requires-Python: >=3.10
Requires-Dist: rich>=14.0.0
